lazydiff/__init__.py
lazydiff/ops.py
lazydiff/regression.py
lazydiff/vars.py
lazydiff-0.1.dist-info/DESCRIPTION.rst
lazydiff-0.1.dist-info/METADATA
lazydiff-0.1.dist-info/RECORD
lazydiff-0.1.dist-info/WHEEL
lazydiff-0.1.dist-info/metadata.json
lazydiff-0.1.dist-info/top_level.txt
