Metadata-Version: 2.0
Name: lazydiff
Version: 0.1
Summary: Simple automatic differentiation
Home-page: https://github.com/CS207-Project-Group-7/cs207-FinalProject
Author: Matteo Zhang, Joseph Davison, Raymond Lin, Zheng Yang
Author-email: mzhangyb@gmail.com, josephddavison@gmail.com, rlin@college.harvard.edu, zhengyang@g.harvard.edu
License: MIT
Platform: UNKNOWN
Requires-Dist: numpy
